RVMLabs/lab1/ALU.v
module ALU(
    input [31:0] A,        // First 32-bit operand
    input [31:0] B,        // Second 32-bit operand
    input [3:0] ALUOp,     // 4-bit control signal to choose operation
    output reg [31:0] Result, // 32-bit output result
    output Zero            // Zero flag to indicate if result is zero
);

    always @(*) begin
        case (ALUOp)
            4'b0000: Result = A + B;         // Addition
            4'b0001: Result = A - B;         // Subtraction
            4'b0010: Result = A & B;         // Bitwise AND
            4'b0011: Result = A | B;         // Bitwise OR
            4'b0100: Result = A ^ B;         // Bitwise XOR
            4'b0101: Result = A << B[4:0];   // Logical shift left
            4'b0110: Result = A >> B[4:0];   // Logical shift right
            4'b0111: Result = $signed(A) >>> B[4:0]; // Arithmetic shift right
            default: Result = 32'b0;         // Default: Zero result
        endcase
    end

    // Zero flag: Set if result is zero
    assign Zero = (Result == 32'b0) ? 1'b1 : 1'b0;

endmodule

RVMLabs/lab1/tb_ALU.v
module tb_ALU; // Testbench module
    reg [31:0] A, B;
    reg [3:0] ALUOp;
    wire [31:0] Result;
    wire Zero;
    // Instantiate the ALU
    ALU uut (
        .A(A),
        .B(B),
        .ALUOp(ALUOp),
        .Result(Result),
        .Zero(Zero)
    );

    initial begin
        // Test addition
        A = 32'h00000005; B = 32'h00000003; ALUOp = 4'b0000;
        #10;
        $display("Addition: A = %h, B = %h, Result = %h, Zero = %b", A, B, Result, Zero);
        // Test subtraction
        A = 32'h00000005; B = 32'h00000005; ALUOp = 4'b0001;
        #10;
        $display("Subtraction: A = %h, B = %h, Result = %h, Zero = %b", A, B, Result, Zero);
        // Test AND
        A = 32'h0000000F; B = 32'h000000F0; ALUOp = 4'b0010;
        #10;
        $display("AND: A = %h, B = %h, Result = %h, Zero = %b", A, B, Result, Zero);
        // Test OR
        A = 32'h0000000F; B = 32'h000000F0; ALUOp = 4'b0011;
        #10;
        $display("OR: A = %h, B = %h, Result = %h, Zero = %b", A, B, Result, Zero);
        // Test XOR
        A = 32'h0000000F; B = 32'h000000F0; ALUOp = 4'b0100;
        #10;
        $display("XOR: A = %h, B = %h, Result = %h, Zero = %b", A, B, Result, Zero);
        // Test shift left
        A = 32'h00000001; B = 32'h00000004; ALUOp = 4'b0101;
        #10;
        $display("Shift Left: A = %h, B = %h, Result = %h, Zero = %b", A, B, Result, Zero);
        // Test shift right
        A = 32'h00000010; B = 32'h00000002; ALUOp = 4'b0110;
        #10;
        $display("Shift Right: A = %h, B = %h, Result = %h, Zero = %b", A, B, Result, Zero);
        // Test arithmetic shift right
        A = 32'h80000000; B = 32'h00000002; ALUOp = 4'b0111;
        #10;
        $display("Arithmetic Shift Right:A = %h,B = %h,Result = %h,Zero = %b",A,B,Result,Zero);
        $finish;
    end
        // Dumping the waveform for GTKWave
    initial begin
        $dumpfile("tb_ALU.vcd");  // Create the VCD 
        $dumpvars(0, tb_ALU);     // Dump variables
    end
endmodule

RVMLabs/lab1/tb_ALU.vcd
$date
	Wed Nov 13 11:44:22 2024
$end
$version
	Icarus Verilog
$end
$timescale
	1s
$end
$scope module tb_ALU $end
$var wire 1 ! Zero $end
$var wire 32 " Result [31:0] $end
$var reg 32 # A [31:0] $end
$var reg 4 $ ALUOp [3:0] $end
$var reg 32 % B [31:0] $end
$scope module uut $end
$var wire 32 & A [31:0] $end
$var wire 4 ' ALUOp [3:0] $end
$var wire 32 ( B [31:0] $end
$var wire 1 ! Zero $end
$var reg 32 ) Result [31:0] $end
$upscope $end
$upscope $end
$enddefinitions $end
$comment Show the parameter values. $end
$dumpall
$end
#0
$dumpvars
b1000 )
b11 (
b0 '
b101 &
b11 %
b0 $
b101 #
b1000 "
0!
$end
#10
1!
b0 "
b0 )
b1 $
b1 '
b101 %
b101 (
#20
b10 $
b10 '
b11110000 %
b11110000 (
b1111 #
b1111 &
#30
0!
b11111111 "
b11111111 )
b11 $
b11 '
#40
b100 $
b100 '
#50
b10000 "
b10000 )
b101 $
b101 '
b100 %
b100 (
b1 #
b1 &
#60
b100 "
b100 )
b110 $
b110 '
b10 %
b10 (
b10000 #
b10000 &
#70
b11100000000000000000000000000000 "
b11100000000000000000000000000000 )
b111 $
b111 '
b10000000000000000000000000000000 #
b10000000000000000000000000000000 &
