codes/lab3/RamChipTwo.v
module RamChipTwo(read_addr,write_addr,in_data,out_data,CLK,WE);
parameter AddressSize=1;
parameter WordSize=1;
input [AddressSize-1:0]read_addr,write_addr;
input [WordSize-1:0]in_data;
output reg [WordSize-1:0]out_data;
input CLK,WE;
// Declare the RAM variable
reg [WordSize-1:0] Mem[0:(1<<AddressSize)-1];
always @ (posedge CLK)
begin
// Write
if (WE)
Mem[write_addr] <= in_data;
out_data <= Mem[read_addr];
end
endmodule

codes/lab3/RamChipTwo_tb.v
module RamChipTwo_tb ();
reg clk_tb =0;
reg[3:0] read_addr_tb, write_addr_tb;
wire[7:0] out_data_tb;
reg[7:0] in_data_tb;
reg we_tb;

defparam mem0.AddressSize=4;
defparam mem0.WordSize=8;
RamChipTwo mem0(read_addr_tb,write_addr_tb,in_data_tb,out_data_tb,clk_tb,we_tb);

initial begin

	$dumpfile("RamChipTwo_wave.vcd");
	$dumpvars;
	write_addr_tb = 4'b0000;
	write_addr_tb = 4'b0000;
	#2 we_tb =1; in_data_tb=8'b11100011;
	#2 $display("write_data=%b, read_data=%b",in_data_tb,out_data_tb);
	#2 write_addr_tb =4'b0001;
	#2 we_tb =1; in_data_tb=8'b10101010;
	#2 $display("write_data=%b, read_data=%b",in_data_tb,out_data_tb);
	#2 we_tb=0;
	#2 read_addr_tb = 4'b0001;
	#2 $display("write_data=%b, read_data=%b",in_data_tb,out_data_tb);
	#2 write_addr_tb = 4'b0010;
	#2 we_tb =1; in_data_tb=8'b11001100;
	#2 $display("write_data=%b, read_data=%b",in_data_tb,out_data_tb);
	#2 we_tb=0;
	#2 read_addr_tb = 4'b0010;
	#2 $display("write_data=%b, read_data=%b",in_data_tb,out_data_tb);
	#2 write_addr_tb = 4'b0011;
	#2 we_tb =1; in_data_tb=8'b1110110;
	#2 $display("write_data=%b, read_data=%b",in_data_tb,out_data_tb);
	#2 we_tb=0;
	#2 read_addr_tb = 4'b0011;
	#2 $display("write_data=%b, read_data=%b",in_data_tb,out_data_tb);
	#100 $finish;
end

always #1 clk_tb =!clk_tb;
endmodule

codes/lab3/RamChipTwo_wave.vcd
$date
	Wed Nov 29 19:17:16 2023
$end
$version
	Icarus Verilog
$end
$timescale
	1s
$end
$scope module RamChipTwo_tb $end
$var wire 8 ! out_data_tb [7:0] $end
$var reg 1 " clk_tb $end
$var reg 8 # in_data_tb [7:0] $end
$var reg 4 $ read_addr_tb [3:0] $end
$var reg 1 % we_tb $end
$var reg 4 & write_addr_tb [3:0] $end
$scope module mem0 $end
$var wire 1 " CLK $end
$var wire 1 % WE $end
$var wire 8 ' in_data [7:0] $end
$var wire 4 ( read_addr [3:0] $end
$var wire 4 ) write_addr [3:0] $end
$var reg 8 * out_data [7:0] $end
$upscope $end
$upscope $end
$enddefinitions $end
#0
$dumpvars
bx *
b0 )
bx (
bx '
b0 &
x%
bx $
bx #
0"
bx !
$end
#1
1"
#2
0"
b11100011 #
b11100011 '
1%
#3
1"
#4
0"
#5
1"
#6
0"
b1 &
b1 )
#7
1"
#8
0"
b10101010 #
b10101010 '
#9
1"
#10
0"
#11
1"
#12
0"
0%
#13
1"
#14
0"
b1 $
b1 (
#15
b10101010 !
b10101010 *
1"
#16
0"
#17
1"
#18
0"
b10 &
b10 )
#19
1"
#20
0"
b11001100 #
b11001100 '
1%
#21
1"
#22
0"
#23
1"
#24
0"
0%
#25
1"
#26
0"
b10 $
b10 (
#27
b11001100 !
b11001100 *
1"
#28
0"
#29
1"
#30
0"
b11 &
b11 )
#31
1"
#32
0"
b1110110 #
b1110110 '
1%
#33
1"
#34
0"
#35
1"
#36
0"
0%
#37
1"
#38
0"
b11 $
b11 (
#39
b1110110 !
b1110110 *
1"
