RVMLabs/lab2/RV32I_external_memories/Decoder.v

//`timescale 1ns / 1ps

module Decoder(
    input wire [31:0] instruction,

    // ISA Opcodes
    output wire ALUReg,           // ALU operation based on register
    output wire ALUImmediate,     // ALU operation based on immediate
    output wire Branch,           // Branch based on immediate
    output wire JALR,             // Jump based on register
    output wire JAL,              // Jump based on immediate
    output wire AUIPC,            // Load value of PC + immediate into destination reg.
    output wire LUI,              // Stores immediate into register
    output wire Load,             // Loads memory at register + immediate into destination reg
    output wire Store,            // Stores value of register 2 into location register + immediate
    output wire System,           // System calls (ecall and ebreak)

    // Register addresses based on instruction
    output wire [4:0] SourceRegister1,     // rs1 in ISA
    output wire [4:0] SourceRegister2,     // rs2 in ISA
    output wire [4:0] DestinationRegister, // rd in ISA

    // ALU operation codes
    output wire [2:0] funct3,
    output wire [6:0] funct7,

    // Immediate values
    output wire [31:0] Iimm,      // Register-Immediate ALU
    output wire [31:0] Simm,      // Store Immediate
    output wire [31:0] Bimm,      // Branch Immediate
    output wire [31:0] Uimm,      // LUI/AUIPC Immediates
    output wire [31:0] Jimm       // Jump Immediates
);

    // Extract fields from the instruction
    wire [6:0] opcode = instruction[6:0];
    assign funct3 = instruction[14:12];
    assign funct7 = instruction[31:25];
    assign SourceRegister1 = instruction[19:15];
    assign SourceRegister2 = instruction[24:20];
    assign DestinationRegister = instruction[11:7];

    // Decode opcodes for each type of instruction
    assign ALUReg = (opcode == 7'b0110011);       // R-type (e.g., ADD, SUB)
    assign ALUImmediate = (opcode == 7'b0010011);  // I-type ALU (e.g., ADDI, ORI)
    assign Branch = (opcode == 7'b1100011);        // B-type (e.g., BEQ, BNE)
    assign JALR = (opcode == 7'b1100111);          // I-type JALR
    assign JAL = (opcode == 7'b1101111);           // J-type JAL
    assign AUIPC = (opcode == 7'b0010111);         // U-type AUIPC
    assign LUI = (opcode == 7'b0110111);           // U-type LUI
    assign Load = (opcode == 7'b0000011);          // I-type Load (e.g., LW)
    assign Store = (opcode == 7'b0100011);         // S-type Store (e.g., SW)
    assign System = (opcode == 7'b1110011);        // System (e.g., ECALL, EBREAK)

    // Immediate generation for different types
    assign Iimm = {{20{instruction[31]}}, instruction[31:20]};            // I-type immediate (12-bit signed)
    assign Simm = {{20{instruction[31]}}, instruction[31:25], instruction[11:7]}; // S-type immediate (12-bit signed)
    assign Bimm = {{19{instruction[31]}}, instruction[31], instruction[7], instruction[30:25], instruction[11:8], 1'b0}; // B-type immediate (13-bit signed)
    assign Uimm = {instruction[31:12], 12'b0};                            // U-type immediate (20-bit, upper 20 bits)
    assign Jimm = {{11{instruction[31]}}, instruction[31], instruction[19:12], instruction[20], instruction[30:21], 1'b0}; // J-type immediate (21-bit signed)

endmodule

RVMLabs/lab2/RV32I_external_memories/tb_Decoder.v
`timescale 1ns / 1ps

module tb_Decoder;

    // Inputs
    reg [31:0] instruction;

    // Outputs
    wire ALUReg;
    wire ALUImmediate;
    wire Branch;
    wire JALR;
    wire JAL;
    wire AUIPC;
    wire LUI;
    wire Load;
    wire Store;
    wire System;

    wire [4:0] SourceRegister1;
    wire [4:0] SourceRegister2;
    wire [4:0] DestinationRegister;

    wire [2:0] funct3;
    wire [6:0] funct7;

    wire [31:0] Iimm;
    wire [31:0] Simm;
    wire [31:0] Bimm;
    wire [31:0] Uimm;
    wire [31:0] Jimm;

    // Instantiate the Decoder
    Decoder uut (
        .instruction(instruction),
        .ALUReg(ALUReg),
        .ALUImmediate(ALUImmediate),
        .Branch(Branch),
        .JALR(JALR),
        .JAL(JAL),
        .AUIPC(AUIPC),
        .LUI(LUI),
        .Load(Load),
        .Store(Store),
        .System(System),
        .SourceRegister1(SourceRegister1),
        .SourceRegister2(SourceRegister2),
        .DestinationRegister(DestinationRegister),
        .funct3(funct3),
        .funct7(funct7),
        .Iimm(Iimm),
        .Simm(Simm),
        .Bimm(Bimm),
        .Uimm(Uimm),
        .Jimm(Jimm)
    );

    // Test cases
    initial begin
        // Test I-type (ADDI)
        instruction = 32'b000000000100_00001_000_00010_0010011; // ADDI x2, x1, 4
        #10;
        $display("ADDI Instruction: ALUImmediate=%b, Iimm=%h", ALUImmediate, Iimm);

        // Test R-type (ADD)
        instruction = 32'b0000000_00010_00001_000_00011_0110011; // ADD x3, x1, x2
        #10;
        $display("ADD Instruction: ALUReg=%b, SourceRegister1=%d, SourceRegister2=%d, DestinationRegister=%d, funct3=%b, funct7=%b",
                 ALUReg, SourceRegister1, SourceRegister2, DestinationRegister, funct3, funct7);

        // Test B-type (BEQ)
        instruction = 32'b0000000_00010_00001_000_000000000110_1100011; // BEQ x1, x2, offset 6
        #10;
        $display("BEQ Instruction: Branch=%b, Bimm=%h", Branch, Bimm);

        // Test U-type (LUI)
        instruction = 32'b00000000000000000001_00000_0110111; // LUI x0, 0x1
        #10;
        $display("LUI Instruction: LUI=%b, Uimm=%h", LUI, Uimm);

        // Test U-type (AUIPC)
        instruction = 32'b00000000000000000010_00001_0010111; // AUIPC x1, 0x2
        #10;
        $display("AUIPC Instruction: AUIPC=%b, Uimm=%h", AUIPC, Uimm);

        // Test J-type (JAL)
        instruction = 32'b00000000000100000000_00001_1101111; // JAL x1, offset 0x100
        #10;
        $display("JAL Instruction: JAL=%b, Jimm=%h", JAL, Jimm);

        // Test I-type (JALR)
        instruction = 32'b000000000100_00001_000_00010_1100111; // JALR x2, x1, 4
        #10;
        $display("JALR Instruction: JALR=%b, Iimm=%h", JALR, Iimm);

        // Test Load (LW)
        instruction = 32'b000000000100_00001_010_00010_0000011; // LW x2, 4(x1)
        #10;
        $display("Load Instruction: Load=%b, Iimm=%h", Load, Iimm);

        // Test Store (SW)
        instruction = 32'b0000000_00010_00001_010_000000001000_0100011; // SW x2, 8(x1)
        #10;
        $display("Store Instruction: Store=%b, Simm=%h", Store, Simm);

        // Test System (ECALL)
        instruction = 32'b00000000000000000000000001110011; // ECALL
        #10;
        $display("System Instruction: System=%b", System);

        // End of test
        $finish;
    end

        // Monitor outputs for debugging
    initial begin
        $dumpfile("tb_Decoder.vcd");  // Create the VCD file
        $dumpvars(0, tb_Decoder);     // Dump variables
    end

endmodule

RVMLabs/lab2/RV32I_internal_memories/tb_Decoder.vcd
$date
	Sat Nov 16 11:27:30 2024
$end
$version
	Icarus Verilog
$end
$timescale
	1ps
$end
$scope module tb_Decoder $end
$var wire 7 ! funct7 [6:0] $end
$var wire 3 " funct3 [2:0] $end
$var wire 32 # Uimm [31:0] $end
$var wire 1 $ System $end
$var wire 1 % Store $end
$var wire 5 & SourceRegister2 [4:0] $end
$var wire 5 ' SourceRegister1 [4:0] $end
$var wire 32 ( Simm [31:0] $end
$var wire 1 ) Load $end
$var wire 1 * LUI $end
$var wire 32 + Jimm [31:0] $end
$var wire 1 , JALR $end
$var wire 1 - JAL $end
$var wire 32 . Iimm [31:0] $end
$var wire 5 / DestinationRegister [4:0] $end
$var wire 1 0 Branch $end
$var wire 32 1 Bimm [31:0] $end
$var wire 1 2 AUIPC $end
$var wire 1 3 ALUReg $end
$var wire 1 4 ALUImmediate $end
$var reg 32 5 instruction [31:0] $end
$scope module uut $end
$var wire 32 6 instruction [31:0] $end
$var wire 7 7 opcode [6:0] $end
$var wire 7 8 funct7 [6:0] $end
$var wire 3 9 funct3 [2:0] $end
$var wire 32 : Uimm [31:0] $end
$var wire 1 $ System $end
$var wire 1 % Store $end
$var wire 5 ; SourceRegister2 [4:0] $end
$var wire 5 < SourceRegister1 [4:0] $end
$var wire 32 = Simm [31:0] $end
$var wire 1 ) Load $end
$var wire 1 * LUI $end
$var wire 32 > Jimm [31:0] $end
$var wire 1 , JALR $end
$var wire 1 - JAL $end
$var wire 32 ? Iimm [31:0] $end
$var wire 5 @ DestinationRegister [4:0] $end
$var wire 1 0 Branch $end
$var wire 32 A Bimm [31:0] $end
$var wire 1 2 AUIPC $end
$var wire 1 3 ALUReg $end
$var wire 1 4 ALUImmediate $end
$upscope $end
$upscope $end
$enddefinitions $end
$comment Show the parameter values. $end
$dumpall
$end
#0
$dumpvars
b10 A
b10 @
b100 ?
b1000000000000100 >
b10 =
b1 <
b100 ;
b10000001000000000000000 :
b0 9
b0 8
b10011 7
b10000001000000100010011 6
b10000001000000100010011 5
14
03
02
b10 1
00
b10 /
b100 .
0-
0,
b1000000000000100 +
0*
0)
b10 (
b1 '
b100 &
0%
0$
b10000001000000000000000 #
b0 "
b0 !
$end
#10000
13
04
b110011 7
b10 &
b10 ;
b11 /
b11 @
b10 .
b10 ?
b11 (
b11 =
b100000000010 1
b100000000010 A
b1000001000000000000000 #
b1000001000000000000000 :
b1000000000000010 +
b1000000000000010 >
b1000001000000110110011 5
b1000001000000110110011 6
#20000
03
10
b1100011 7
b1000 !
b1000 8
b0 '
b0 <
b100 &
b100 ;
b110 /
b110 @
b100000100 .
b100000100 ?
b100000110 (
b100000110 =
b100000110 1
b100000110 A
b10000010000000000000000000000 #
b10000010000000000000000000000 :
b100000100 +
b100000100 >
b10000010000000000001101100011 5
b10000010000000000001101100011 6
#30000
00
1*
b110111 7
b1 "
b1 9
b0 !
b0 8
b0 &
b0 ;
b0 /
b0 @
b0 .
b0 ?
b0 (
b0 =
b0 1
b0 A
b1000000000000 #
b1000000000000 :
b1000000000000 +
b1000000000000 >
b1000000110111 5
b1000000110111 6
#40000
12
0*
b10111 7
b10 "
b10 9
b1 /
b1 @
b1 (
b1 =
b100000000000 1
b100000000000 A
b10000000000000 #
b10000000000000 :
b10000000000000 +
b10000000000000 >
b10000010010111 5
b10000010010111 6
#50000
1-
02
b1101111 7
b0 "
b0 9
b1 &
b1 ;
b1 .
b1 ?
b100000000000000000000 #
b100000000000000000000 :
b100000000000 +
b100000000000 >
b100000000000011101111 5
b100000000000011101111 6
#60000
1,
0-
b1100111 7
b1 '
b1 <
b100 &
b100 ;
b10 /
b10 @
b100 .
b100 ?
b10 (
b10 =
b10 1
b10 A
b10000001000000000000000 #
b10000001000000000000000 :
b1000000000000100 +
b1000000000000100 >
b10000001000000101100111 5
b10000001000000101100111 6
#70000
0,
1)
b11 7
b10 "
b10 9
b10000001010000000000000 #
b10000001010000000000000 :
b1010000000000100 +
b1010000000000100 >
b10000001010000100000011 5
b10000001010000100000011 6
#80000
0)
1%
b100011 7
b0 "
b0 9
b1000 !
b1000 8
b0 '
b0 <
b101 &
b101 ;
b1000 /
b1000 @
b100000101 .
b100000101 ?
b100001000 (
b100001000 =
b100001000 1
b100001000 A
b10000010100000000000000000000 #
b10000010100000000000000000000 :
b100100000100 +
b100100000100 >
b10000010100000000010000100011 5
b10000010100000000010000100011 6
#90000
0%
1$
b1110011 7
b0 !
b0 8
b0 &
b0 ;
b0 /
b0 @
b0 .
b0 ?
b0 (
b0 =
b0 1
b0 A
b0 #
b0 :
b0 +
b0 >
b1110011 5
b1110011 6
