RVMLabs/lab2/RV32I_internal_memories/ALU.v
module ALU (
    input wire [31:0] instruction,
    input wire [31:0] ALUVAL1,           // Register Source 1
    input wire ALUReg,                   // Control signal to select register source 2
    input wire ALUImmediate,             // Control signal to select immediate
    input wire [31:0] ALUREGVAl2,        // Value from register source 2
    input wire [31:0] Iimm,              // Immediate value
    input wire [2:0] funct3,             // Function code (3 bits)
    input wire [6:0] funct7,             // Function code (7 bits)
    output reg [31:0] ALUOut             // ALU output to the destination register
);

    wire [31:0] ALUOperand2;

    // Select the second operand based on control signals
    assign ALUOperand2 = (ALUReg) ? ALUREGVAl2 : 
                         (ALUImmediate) ? Iimm : 
                         32'b0;

    always @(*) begin
        case (funct3)
            3'b000: begin
                // ADD or SUB
                if (funct7 == 7'b0100000)  // SUB (funct7 = 0x20)
                    ALUOut = ALUVAL1 - ALUOperand2;
                else                       // ADD (funct7 = 0x00)
                    ALUOut = ALUVAL1 + ALUOperand2;
            end

            3'b001: begin
                // SLL (Shift Left Logical)
                ALUOut = ALUVAL1 << ALUOperand2[4:0];
            end

            3'b010: begin
                // SLT (Set Less Than)
                ALUOut = ($signed(ALUVAL1) < $signed(ALUOperand2)) ? 32'b1 : 32'b0;
            end

            3'b011: begin
                // SLTU (Set Less Than Unsigned)
                ALUOut = (ALUVAL1 < ALUOperand2) ? 32'b1 : 32'b0;
            end

            3'b100: begin
                // XOR
                ALUOut = ALUVAL1 ^ ALUOperand2;
            end

            3'b101: begin
                // SRL or SRA (Shift Right Logical/Arithmetic)
                if (funct7 == 7'b0100000)  // SRA (Arithmetic shift right)
                    ALUOut = $signed(ALUVAL1) >>> ALUOperand2[4:0];
                else                       // SRL (Logical shift right)
                    ALUOut = ALUVAL1 >> ALUOperand2[4:0];
            end

            3'b110: begin
                // OR
                ALUOut = ALUVAL1 | ALUOperand2;
            end

            3'b111: begin
                // AND
                ALUOut = ALUVAL1 & ALUOperand2;
            end

            default: begin
                // Default case, output zero
                ALUOut = 32'b0;
            end
        endcase
    end
endmodule

RVMLabs/lab2/RV32I_internal_memories/tb_ALU.v
`timescale 1ns / 1ps

module tb_ALU;

    // Inputs
    reg [31:0] instruction;
    reg [31:0] ALUVAL1;
    reg ALUReg;
    reg ALUImmediate;
    reg [31:0] ALUREGVAl2;
    reg [31:0] Iimm;
    reg [2:0] funct3;
    reg [6:0] funct7;

    // Output
    wire [31:0] ALUOut;

    // Instantiate the ALU
    ALU uut (
        .instruction(instruction),
        .ALUVAL1(ALUVAL1),
        .ALUReg(ALUReg),
        .ALUImmediate(ALUImmediate),
        .ALUREGVAl2(ALUREGVAl2),
        .Iimm(Iimm),
        .funct3(funct3),
        .funct7(funct7),
        .ALUOut(ALUOut)
    );

    // Test cases
    initial begin
        // Initialize inputs
        ALUVAL1 = 32'h0000000F;   // Operand 1
        ALUREGVAl2 = 32'h00000003; // Operand 2
        Iimm = 32'h00000004;      // Immediate value

        // Test ADDI (Addition with Immediate)
        ALUReg = 0;
        ALUImmediate = 1;
        funct3 = 3'b000;
        funct7 = 7'b0000000;
        #10;
        $display("ADDI: %h + %h = %h", ALUVAL1, Iimm, ALUOut);

        // Test ADD (Addition with Register)
        ALUReg = 1;
        ALUImmediate = 0;
        funct3 = 3'b000;
        funct7 = 7'b0000000;
        #10;
        $display("ADD: %h + %h = %h", ALUVAL1, ALUREGVAl2, ALUOut);

        // Test SUB (Subtraction)
        funct7 = 7'b0100000;
        #10;
        $display("SUB: %h - %h = %h", ALUVAL1, ALUREGVAl2, ALUOut);

        // Test ANDI (AND with Immediate)
        ALUReg = 0;
        ALUImmediate = 1;
        funct3 = 3'b111;
        funct7 = 7'b0000000;
        #10;
        $display("ANDI: %h & %h = %h", ALUVAL1, Iimm, ALUOut);

        // Test ORI (OR with Immediate)
        funct3 = 3'b110;
        #10;
        $display("ORI: %h | %h = %h", ALUVAL1, Iimm, ALUOut);

        // Test XORI (XOR with Immediate)
        funct3 = 3'b100;
        #10;
        $display("XORI: %h ^ %h = %h", ALUVAL1, Iimm, ALUOut);

        // Test SLLI (Shift Left Logical Immediate)
        funct3 = 3'b001;
        #10;
        $display("SLLI: %h << %h = %h", ALUVAL1, Iimm[4:0], ALUOut);

        // Test SRLI (Shift Right Logical Immediate)
        funct3 = 3'b101;
        funct7 = 7'b0000000;
        #10;
        $display("SRLI: %h >> %h = %h", ALUVAL1, Iimm[4:0], ALUOut);

        // Test SRAI (Shift Right Arithmetic Immediate)
        funct7 = 7'b0100000;
        #10;
        $display("SRAI: %h >>> %h = %h", ALUVAL1, Iimm[4:0], ALUOut);

        // Test SLT (Set Less Than, signed comparison)
        ALUReg = 1;
        ALUImmediate = 0;
        funct3 = 3'b010;
        funct7 = 7'b0000000;
        ALUVAL1 = 32'hFFFFFFFE;  // -2 in two's complement
        ALUREGVAl2 = 32'h00000001; // +1
        #10;
        $display("SLT: %h < %h = %h", ALUVAL1, ALUREGVAl2, ALUOut);

        // Test SLTU (Set Less Than Unsigned)
        funct3 = 3'b011;
        ALUVAL1 = 32'h00000001; // 1
        ALUREGVAl2 = 32'hFFFFFFFF; // Large unsigned value
        #10;
        $display("SLTU: %h < %h = %h", ALUVAL1, ALUREGVAl2, ALUOut);

        // End of test
        $finish;
    end

        initial begin
        $dumpfile("tb_ALU.vcd");  // Create the VCD file
        $dumpvars(0, tb_ALU);     // Dump variables
    end

endmodule

RVMLabs/lab2/RV32I_external_memories/tb_ALU.vcd
$date
	Sat Nov 16 11:10:56 2024
$end
$version
	Icarus Verilog
$end
$timescale
	1ps
$end
$scope module tb_ALU $end
$var wire 32 ! ALUOut [31:0] $end
$var reg 1 " ALUImmediate $end
$var reg 32 # ALUREGVAl2 [31:0] $end
$var reg 1 $ ALUReg $end
$var reg 32 % ALUVAL1 [31:0] $end
$var reg 32 & Iimm [31:0] $end
$var reg 3 ' funct3 [2:0] $end
$var reg 7 ( funct7 [6:0] $end
$var reg 32 ) instruction [31:0] $end
$scope module uut $end
$var wire 1 " ALUImmediate $end
$var wire 32 * ALUREGVAl2 [31:0] $end
$var wire 1 $ ALUReg $end
$var wire 32 + ALUVAL1 [31:0] $end
$var wire 32 , Iimm [31:0] $end
$var wire 3 - funct3 [2:0] $end
$var wire 7 . funct7 [6:0] $end
$var wire 32 / instruction [31:0] $end
$var wire 32 0 ALUOperand2 [31:0] $end
$var reg 32 1 ALUOut [31:0] $end
$upscope $end
$upscope $end
$enddefinitions $end
$comment Show the parameter values. $end
$dumpall
$end
#0
$dumpvars
b10011 1
b100 0
bx /
b0 .
b0 -
b100 ,
b1111 +
b11 *
bx )
b0 (
b0 '
b100 &
b1111 %
0$
b11 #
1"
b10011 !
$end
#10000
b10010 !
b10010 1
b11 0
0"
1$
#20000
b1100 !
b1100 1
b100000 (
b100000 .
#30000
b100 !
b100 1
b100 0
b0 (
b0 .
b111 '
b111 -
1"
0$
#40000
b1111 !
b1111 1
b110 '
b110 -
#50000
b1011 !
b1011 1
b100 '
b100 -
#60000
b11110000 !
b11110000 1
b1 '
b1 -
#70000
b0 !
b0 1
b101 '
b101 -
#80000
b100000 (
b100000 .
#90000
b1 !
b1 1
b1 0
b1 #
b1 *
b11111111111111111111111111111110 %
b11111111111111111111111111111110 +
b0 (
b0 .
b10 '
b10 -
0"
1$
#100000
b11111111111111111111111111111111 0
b1 !
b1 1
b11111111111111111111111111111111 #
b11111111111111111111111111111111 *
b1 %
b1 +
b11 '
b11 -
